mikroe-uhb
setup.py
mikroe_uhb.egg-info/PKG-INFO
mikroe_uhb.egg-info/SOURCES.txt
mikroe_uhb.egg-info/dependency_links.txt
mikroe_uhb.egg-info/requires.txt
mikroe_uhb.egg-info/top_level.txt
mikroeuhb/__init__.py
mikroeuhb/bootinfo.py
mikroeuhb/device.py
mikroeuhb/devkit.py
mikroeuhb/hexfile.py
mikroeuhb/util.py
mikroeuhb/hid/__init__.py
mikroeuhb/hid/generic.py
mikroeuhb/hid/linux.py