Metadata-Version: 1.1
Name: mikroe-uhb
Version: 0.2
Summary: USB HID Bootloader programmer for MikroElektronika devices
Home-page: https://github.com/thotypous/mikroe-uhb
Author: UNKNOWN
Author-email: UNKNOWN
License: UNKNOWN
Download-URL: https://github.com/thotypous/mikroe-uhb/archive/v0.2.tar.gz
Keywords: microcontroller,usb,programmer
Platform: UNKNOWN
